squeeql/__init__.py
squeeql/migrator.py
squeeql/utils.py
squeeql/tests/__init__.py
squeeql/tests/test_migrator.py
squeeql/tests/test_utils.py
squeeql-2025.8.2.dist-info/licenses/COPYING
squeeql-2025.8.2.dist-info/METADATA
squeeql-2025.8.2.dist-info/WHEEL
squeeql-2025.8.2.dist-info/top_level.txt
squeeql-2025.8.2.dist-info/RECORD
