Metadata-Version: 2.4
Name: squeeql
Version: 2025.8.2
Summary: Simple utilities for using sqlite3.
Project-URL: Repository, https://github.com/squeeql-dev/squeeql
Project-URL: Issues, https://github.com/squeeql-dev/squeeql/issues
Requires-Python: >=3.10
License-File: COPYING
Provides-Extra: test
Requires-Dist: black>=24.10.0; extra == "test"
Requires-Dist: parameterized>=0.9.0; extra == "test"
Requires-Dist: pytest>=8.3.5; extra == "test"
Requires-Dist: pytest-cov<6.0,>=5.0.0; extra == "test"
Dynamic: license-file
